ads/__init__.py
ads/__main__.py
ads/ads.py
ads/terminal.py
adscli-0.8.6.dist-info/DESCRIPTION.rst
adscli-0.8.6.dist-info/METADATA
adscli-0.8.6.dist-info/RECORD
adscli-0.8.6.dist-info/WHEEL
adscli-0.8.6.dist-info/entry_points.txt
adscli-0.8.6.dist-info/metadata.json
adscli-0.8.6.dist-info/top_level.txt
