Metadata-Version: 2.0
Name: adscli
Version: 0.8.6
Summary: Start, stop, and manage microservices in a codebase
Home-page: https://github.com/adamcath/ads
Author: Adam Cath
Author-email: adam.cath@gmail.com
License: MIT
Keywords: microservice tool launcher upstart init.d
Platform: UNKNOWN
Classifier: Development Status :: 4 - Beta
Classifier: Environment :: MacOS X
Classifier: Intended Audience :: Developers
Classifier: License :: OSI Approved :: MIT License
Classifier: Programming Language :: Python :: 2.7
Classifier: Topic :: Utilities
Classifier: Topic :: Software Development
Requires-Dist: pyyaml (>=3.11)
